smopy.py
smopy-0.0.8.dist-info/LICENSE
smopy-0.0.8.dist-info/METADATA
smopy-0.0.8.dist-info/WHEEL
smopy-0.0.8.dist-info/top_level.txt
smopy-0.0.8.dist-info/RECORD
