Metadata-Version: 2.1
Name: smopy
Version: 0.0.8
Summary: OpenStreetMap image tiles in Python
Home-page: https://github.com/rossant/smopy
Author: Cyrille Rossant
Author-email: rossant@users.noreply.github.com
License: BSD
Keywords: openstreetmap matplotlib map maps ipython
Platform: UNKNOWN
Classifier: Development Status :: 3 - Alpha
Classifier: Topic :: Utilities
Classifier: Framework :: IPython
Classifier: License :: OSI Approved :: BSD License
Provides-Extra: ipython
License-File: LICENSE
